MS2Function/MS2BioTextDataset.py
MS2Function/__init__.py
MS2Function/assets.py
MS2Function/biotext_processor.py
MS2Function/config.py
MS2Function/data_augmentation.py
MS2Function/gpt_inference.py
MS2Function/llm_client.py
MS2Function/model_manager.py
MS2Function/pubmed.py
MS2Function/read_raw_data.py
MS2Function/utils.py
MS2Function/workflow.py
MS2Function/model/MS2BioText.py
MS2Function/model/MSBERT.py
MS2Function/model/__init__.py
MS2Function/model/config.py
MS2Function/model/utils.py
ms2function-0.1.1.dist-info/LICENSE
ms2function-0.1.1.dist-info/METADATA
ms2function-0.1.1.dist-info/WHEEL
ms2function-0.1.1.dist-info/top_level.txt
ms2function-0.1.1.dist-info/RECORD
