Metadata-Version: 2.1
Name: ms2function
Version: 0.1.1
Summary: Deep learning model for MS2 data annotation
Home-page: https://huggingface.co/cgxjdzz/ms2function-assets
Author: User
Classifier: Programming Language :: Python :: 3
Classifier: Operating System :: OS Independent
Requires-Python: >=3.8
License-File: LICENSE
Requires-Dist: torch
Requires-Dist: transformers
Requires-Dist: numpy
Requires-Dist: pandas
Requires-Dist: scikit-learn
Requires-Dist: tqdm
Requires-Dist: wandb
Requires-Dist: huggingface-hub
